PairedCompCalc/__init__.py
PairedCompCalc/gauss_gamma.py
PairedCompCalc/gauss_gamma_null.py
PairedCompCalc/pc_data.py
PairedCompCalc/pc_display.py
PairedCompCalc/pc_display_format.py
PairedCompCalc/pc_file.py
PairedCompCalc/pc_file_res.py
PairedCompCalc/pc_latent.py
PairedCompCalc/pc_logging.py
PairedCompCalc/pc_model.py
PairedCompCalc/pc_planning.py
PairedCompCalc/pc_simulation.py
PairedCompCalc/pc_subject.py
PairedCompCalc/run_pc.py
PairedCompCalc/run_plan.py
PairedCompCalc/run_sim.py
PairedCompCalc/safe_logistic.py
PairedCompCalc-2.1.1.dist-info/LICENSE.txt
PairedCompCalc-2.1.1.dist-info/METADATA
PairedCompCalc-2.1.1.dist-info/WHEEL
PairedCompCalc-2.1.1.dist-info/top_level.txt
PairedCompCalc-2.1.1.dist-info/RECORD
