Metadata-Version: 2.1
Name: PairedCompCalc
Version: 2.1.1
Summary: Statistical Analysis of Paired-Comparison Data
Author: Arne Leijon
Author-email: leijon@kth.se
License: MIT License
Keywords: paired-comparison,Bayesian,psycho-physics
Classifier: Development Status :: 5 - Production/Stable
Classifier: Programming Language :: Python :: 3.9
Classifier: License :: OSI Approved :: MIT License
Classifier: Operating System :: OS Independent
Classifier: Intended Audience :: Science/Research
Classifier: Topic :: Scientific/Engineering :: Information Analysis
Classifier: Topic :: Multimedia :: Sound/Audio
Requires-Python: >=3.9
License-File: LICENSE.txt
Requires-Dist: numpy (>=1.22)
Requires-Dist: scipy (>=1.7)
Requires-Dist: matplotlib (>=3.6.2)
Requires-Dist: samppy (>=1.3)
Requires-Dist: pandas (>=2.0.1)
Requires-Dist: openpyxl (>=3.0)
